kneeseg/__init__.py
kneeseg/bone_rf.py
kneeseg/features.py
kneeseg/io.py
kneeseg/random_walker.py
kneeseg/registration.py
kneeseg/rf_seg.py
kneeseg/validate_config.py
kneeseg/configs/config_schema.json
kneeseg/configs/ski10_full_inference_config.json
kneeseg/configs/ski10_full_train_config.json
kneeseg/data/ski10_all_train_split.json
kneeseg/data/ski10_full_split.json
kneeseg/pipeline/__init__.py
kneeseg/pipeline/inference.py
kneeseg/pipeline/run.py
kneeseg/pipeline/train.py
kneeseg/tests/__init__.py
kneeseg/tests/test_core.py
kneeseg/tests/test_features.py
kneeseg/tests/test_io.py
kneeseg-0.1.3.dist-info/licenses/LICENSE
kneeseg-0.1.3.dist-info/METADATA
kneeseg-0.1.3.dist-info/WHEEL
kneeseg-0.1.3.dist-info/entry_points.txt
kneeseg-0.1.3.dist-info/top_level.txt
kneeseg-0.1.3.dist-info/RECORD
