Metadata-Version: 2.4
Name: kneeseg
Version: 0.1.3
Summary: A Python reimplementation of Semantic Context Forests for Learning-Based Knee Cartilage Segmentation in 3D MR Images
Author-email: Quan Wang <quanw@google.com>
License-Expression: MIT
Classifier: Programming Language :: Python :: 3
Classifier: Operating System :: OS Independent
Requires-Python: >=3.8
License-File: LICENSE
Requires-Dist: numpy
Requires-Dist: scipy
Requires-Dist: scikit-learn
Requires-Dist: joblib
Requires-Dist: tqdm
Requires-Dist: SimpleITK
Dynamic: license-file
